password/__init__.py
password/core.py
password_toolkit-0.1.0.dist-info/LICENSE
password_toolkit-0.1.0.dist-info/METADATA
password_toolkit-0.1.0.dist-info/WHEEL
password_toolkit-0.1.0.dist-info/top_level.txt
password_toolkit-0.1.0.dist-info/RECORD
